junco_sync/__init__.py
junco_sync/_modidx.py
junco_sync/cli.py
junco_sync/config.py
junco_sync/sync.py
junco_sync-0.0.4.dist-info/licenses/LICENSE
junco_sync-0.0.4.dist-info/METADATA
junco_sync-0.0.4.dist-info/WHEEL
junco_sync-0.0.4.dist-info/entry_points.txt
junco_sync-0.0.4.dist-info/top_level.txt
junco_sync-0.0.4.dist-info/RECORD
