Metadata-Version: 2.4
Name: junco-sync
Version: 0.0.4
Summary: Sync Snowflake to DuckDB
Home-page: https://github.com/cooper-richason/junco-sync
Author: Cooper Richason
Author-email: 144618753+cooper-richason@users.noreply.github.com
License: Apache Software License 2.0
Keywords: nbdev jupyter notebook python
Classifier: Development Status :: 4 - Beta
Classifier: Intended Audience :: Developers
Classifier: Natural Language :: English
Classifier: Programming Language :: Python :: 3.9
Classifier: Programming Language :: Python :: 3.10
Classifier: Programming Language :: Python :: 3.11
Classifier: Programming Language :: Python :: 3.12
Classifier: License :: OSI Approved :: Apache Software License
Requires-Python: >=3.9
License-File: LICENSE
Requires-Dist: pandas
Requires-Dist: snowflake-connector-python
Requires-Dist: duckdb
Requires-Dist: appdirs
Requires-Dist: click
Provides-Extra: dev
Requires-Dist: nbdev; extra == "dev"
Requires-Dist: fastcore; extra == "dev"
Dynamic: author
Dynamic: author-email
Dynamic: classifier
Dynamic: description
Dynamic: description-content-type
Dynamic: home-page
Dynamic: keywords
Dynamic: license
Dynamic: license-file
Dynamic: provides-extra
Dynamic: requires-dist
Dynamic: requires-python
Dynamic: summary
